railwaypacriman/__init__.py
railwaypacriman/config.py
railwaypacriman/ekidatajp.py
railwaypacriman/join.py
railwaypacriman/line.py
railwaypacriman/logger.py
railwaypacriman/progress.py
railwaypacriman/rpinfo.py
railwaypacriman/rpprogress.py
railwaypacriman/ekidatajp/company20240328.csv
railwaypacriman/ekidatajp/join20240426.csv
railwaypacriman/ekidatajp/line20240426free.csv
railwaypacriman/ekidatajp/station20240426free.csv
railwaypacriman-0.0.3.dist-info/METADATA
railwaypacriman-0.0.3.dist-info/WHEEL
railwaypacriman-0.0.3.dist-info/entry_points.txt
railwaypacriman-0.0.3.dist-info/top_level.txt
railwaypacriman-0.0.3.dist-info/RECORD
