Metadata-Version: 2.1
Name: railwaypacriman
Version: 0.0.3
Summary: Railway-related-activity progress manager
Home-page: UNKNOWN
Author: IppeiKISHIDA
License: MIT
Platform: UNKNOWN
Requires-Dist: graphviz
Requires-Dist: networkx
Requires-Dist: pandas
